zpocr/__init__.py
zpocr/zpocr.py
zpocr-0.0.5.dist-info/METADATA
zpocr-0.0.5.dist-info/WHEEL
zpocr-0.0.5.dist-info/top_level.txt
zpocr-0.0.5.dist-info/RECORD
