Metadata-Version: 2.1
Name: zpocr
Version: 0.0.5
Summary: UNKNOWN
Home-page: UNKNOWN
License: UNKNOWN
Platform: UNKNOWN
Requires-Dist: easyocr
